{"v":5,"entries":{"stories-1-intro--docs":{"id":"stories-1-intro--docs","title":"stories/1. Intro","name":"Docs","importPath":"./src/stories/1. Intro.mdx","storiesImports":[],"type":"docs","tags":["dev","test","unattached-mdx"]},"stories-2-map--docs":{"id":"stories-2-map--docs","title":"stories/2. Map","name":"Docs","importPath":"./src/stories/2. Map.mdx","storiesImports":[],"type":"docs","tags":["dev","test","unattached-mdx"]},"stories-3-filter--docs":{"id":"stories-3-filter--docs","title":"stories/3. Filter","name":"Docs","importPath":"./src/stories/3. Filter.mdx","storiesImports":[],"type":"docs","tags":["dev","test","unattached-mdx"]},"stories-4-reduce--docs":{"id":"stories-4-reduce--docs","title":"stories/4. Reduce","name":"Docs","importPath":"./src/stories/4. Reduce.mdx","storiesImports":[],"type":"docs","tags":["dev","test","unattached-mdx"]},"stories-5-sort--docs":{"id":"stories-5-sort--docs","title":"stories/5. Sort","name":"Docs","importPath":"./src/stories/5. Sort.mdx","storiesImports":[],"type":"docs","tags":["dev","test","unattached-mdx"]},"stories-6-some--docs":{"id":"stories-6-some--docs","title":"stories/6. Some","name":"Docs","importPath":"./src/stories/6. Some.mdx","storiesImports":[],"type":"docs","tags":["dev","test","unattached-mdx"]}}}
